{
  "alerting": true,
  "annotations": true,
  "backend": true,
  "category": "tsdb",
  "dependencies": {
    "grafanaDependency": "\u003e=8.0.0",
    "plugins": []
  },
  "executable": "gpx_timestream",
  "id": "grafana-timestream-datasource",
  "includes": [
    {
      "name": "Sample (DevOps)",
      "path": "dashboards/sample.json",
      "type": "dashboard"
    }
  ],
  "info": {
    "author": {
      "name": "Grafana Labs",
      "url": "https://grafana.com"
    },
    "build": {
      "time": 1706526503659,
      "repo": "https://github.com/grafana/timestream-datasource",
      "branch": "main",
      "hash": "f035c9244076e09aa67366bc751ff427961207a9",
      "build": 520
    },
    "description": "Managed timeseries database from amazon",
    "keywords": [
      "datasource",
      "timestream",
      "aws"
    ],
    "links": [
      {
        "name": "Website",
        "url": "https://github.com/grafana/timestream-datasource"
      }
    ],
    "logos": {
      "large": "img/timestream.svg",
      "small": "img/timestream.svg"
    },
    "screenshots": [],
    "updated": "2024-01-29",
    "version": "2.9.1"
  },
  "metrics": true,
  "name": "Amazon Timestream",
  "type": "datasource"
}